lab_3_package/__init__.py
lab_3_package/cli.py
lab_3_package/common.py
lab_3_package/lab_3_package.py
lab3_for_PyPI-1.1.3.dist-info/AUTHORS.rst
lab3_for_PyPI-1.1.3.dist-info/LICENSE
lab3_for_PyPI-1.1.3.dist-info/METADATA
lab3_for_PyPI-1.1.3.dist-info/WHEEL
lab3_for_PyPI-1.1.3.dist-info/entry_points.txt
lab3_for_PyPI-1.1.3.dist-info/top_level.txt
lab3_for_PyPI-1.1.3.dist-info/RECORD
