Metadata-Version: 2.2
Name: lab3-for-PyPI
Version: 1.1.3
Summary: This is a package created for lab 3.
Author-email: Lazy Bones <cbrigh16@vols.utk.edu>
License: MIT License
Project-URL: Homepage, https://github.com/LazyBonesGIS/lab3
Keywords: lab3
Classifier: Intended Audience :: Developers
Classifier: License :: OSI Approved :: MIT License
Classifier: Natural Language :: English
Classifier: Programming Language :: Python :: 3.8
Classifier: Programming Language :: Python :: 3.9
Classifier: Programming Language :: Python :: 3.10
Classifier: Programming Language :: Python :: 3.11
Classifier: Programming Language :: Python :: 3.12
Requires-Python: >=3.8
License-File: LICENSE
License-File: AUTHORS.rst
Requires-Dist: numpy
Provides-Extra: all
Requires-Dist: lab3[extra]; extra == "all"
Provides-Extra: extra
Requires-Dist: pandas; extra == "extra"
